SoulsSaveCLI/__init__.py
SoulsSaveCLI/soulsave/__init__.py
SoulsSaveCLI/soulsave/core.py
SoulsSaveCLI/soulsave/soulsave.py
SoulsSaveCLI/utils/__init__.py
SoulsSaveCLI/utils/callbacks.py
SoulsSaveCLI/utils/side_functions.py
soulsave-0.1.3.dist-info/LICENSE
soulsave-0.1.3.dist-info/METADATA
soulsave-0.1.3.dist-info/WHEEL
soulsave-0.1.3.dist-info/entry_points.txt
soulsave-0.1.3.dist-info/top_level.txt
soulsave-0.1.3.dist-info/RECORD
